src/ML_veg_reclass.py
src/ML_veg_train.py
src/ML_vegfilter.py
src/__init__.py
src/argclass.py
src/fileio.py
src/miscfx.py
src/model_class.py
src/modelbuilder.py
src/tk_get_user_input.py
src/tk_get_user_input_RECLASS_ONLY.py
src/tk_get_user_input_TRAIN_ONLY.py
src/vegindex.py
veg_seg/__init__.py
veg_seg/main.py
veg_seg/src/ML_veg_reclass.py
veg_seg/src/ML_veg_train.py
veg_seg/src/ML_vegfilter.py
veg_seg/src/__init__.py
veg_seg/src/argclass.py
veg_seg/src/fileio.py
veg_seg/src/miscfx.py
veg_seg/src/model_class.py
veg_seg/src/modelbuilder.py
veg_seg/src/tk_get_user_input.py
veg_seg/src/tk_get_user_input_RECLASS_ONLY.py
veg_seg/src/tk_get_user_input_TRAIN_ONLY.py
veg_seg/src/vegindex.py
veg_seg-0.1.2.dist-info/LICENSE.txt
veg_seg-0.1.2.dist-info/METADATA
veg_seg-0.1.2.dist-info/WHEEL
veg_seg-0.1.2.dist-info/entry_points.txt
veg_seg-0.1.2.dist-info/top_level.txt
veg_seg-0.1.2.dist-info/RECORD
