Metadata-Version: 2.2
Name: veg_seg
Version: 0.1.2
Summary: A package for classifying vegetation from lidar point clouds
Home-page: https://github.com/pwernet/MLP_veg_seg
Author: Phillipe Wernette
Author-email: pwernett@msu.edu
License: MIT
Classifier: Development Status :: 3 - Alpha
Classifier: Intended Audience :: Science/Research
Classifier: Topic :: Scientific/Engineering :: GIS
Classifier: License :: OSI Approved :: MIT License
Classifier: Programming Language :: Python :: 3.10
Classifier: Operating System :: OS Independent
License-File: LICENSE.txt
Requires-Dist: matplotlib
Requires-Dist: ipython
Requires-Dist: graphviz
Requires-Dist: scikit-learn
Requires-Dist: pandas
Requires-Dist: geopandas
Requires-Dist: scipy
Requires-Dist: tqdm
Requires-Dist: pydot
Requires-Dist: laspy
Requires-Dist: lazrs
Requires-Dist: numpy==1.26.4; platform_system == "Windows"
Requires-Dist: tensorflow[and-cuda]==2.17; platform_system == "Linux"
Requires-Dist: tensorflow-gpu==2.10.1; platform_system == "Windows"
Dynamic: author
Dynamic: author-email
Dynamic: classifier
Dynamic: description
Dynamic: description-content-type
Dynamic: home-page
Dynamic: license
Dynamic: requires-dist
Dynamic: summary
